{
  "signedContributors": [
    {
      "name": "eriksaulnier",
      "id": 1200065,
      "comment_id": "",
      "created_at": "2026-03-18T21:31:03Z",
      "repoId": "",
      "pullRequestNo": 4
    },
    {
      "name": "ShaneHoffman",
      "id": 90718732,
      "comment_id": "",
      "created_at": "2026-03-25T21:57:50Z",
      "repoId": "",
      "pullRequestNo": 13
    },
    {
      "name": "richarddrum",
      "id": 26073504,
      "comment_id": "",
      "created_at": "2026-03-25T23:10:01Z",
      "repoId": "",
      "pullRequestNo": 14
    },
    {
      "name": "cmcmanus96",
      "id": 35268790,
      "comment_id": 4139754396,
      "created_at": "2026-03-27T02:45:25Z",
      "repoId": 1164206183,
      "pullRequestNo": 15
    },
    {
      "name": "bgreater",
      "id": 152350,
      "comment_id": 4171306479,
      "created_at": "2026-04-01T16:30:46Z",
      "repoId": 1164206183,
      "pullRequestNo": 18
    }
  ]
}